pytypecho/__init__.py
pytypecho/aio.py
pytypecho/log.py
pytypecho/main.py
pytypecho/models.py
pytypecho-2.1.0.dist-info/LICENSE
pytypecho-2.1.0.dist-info/METADATA
pytypecho-2.1.0.dist-info/WHEEL
pytypecho-2.1.0.dist-info/top_level.txt
pytypecho-2.1.0.dist-info/RECORD
