Metadata-Version: 2.1
Name: pytypecho
Version: 2.1.0
Summary: Python Typecho Client (XMLRPC)
Home-page: https://github.com/veoco/PyTypecho
Author: Veoco
Author-email: one@nomox.cn
License: UNKNOWN
Platform: UNKNOWN
Classifier: Programming Language :: Python :: 3
Classifier: License :: OSI Approved :: MIT License
Classifier: Operating System :: OS Independent
License-File: LICENSE
